com/__init__.py
com/istackvip/__init__.py
com/istackvip/hutool/__init__.py
hutool-1.0.0.dist-info/LICENSE.txt
hutool-1.0.0.dist-info/METADATA
hutool-1.0.0.dist-info/WHEEL
hutool-1.0.0.dist-info/top_level.txt
hutool-1.0.0.dist-info/RECORD
