Metadata-Version: 2.1
Name: hutool
Version: 1.0.0
Summary: Hutool for Python
Home-page: https://istackvip.com
Author: isaiah
Author-email: isaiah@sohu.com
License: MIT
Project-URL: Documentation, https://packaging.python.org/tutorials/distributing-packages/
Project-URL: Funding, https://donate.pypi.org
Project-URL: Say Thanks!, http://saythanks.io/to/example
Project-URL: Source, https://github.com/pypa/sampleproject/
Project-URL: Tracker, https://github.com/pypa/sampleproject/issues
Keywords: sample tool library
Platform: UNKNOWN
Classifier: Development Status :: 3 - Alpha
Classifier: Intended Audience :: Developers
Classifier: Topic :: Software Development :: Build Tools
Classifier: License :: OSI Approved :: MIT License
Classifier: Programming Language :: Python :: 3
Classifier: Programming Language :: Python :: 3.2
Classifier: Programming Language :: Python :: 3.3
Classifier: Programming Language :: Python :: 3.4
Requires-Python: >=3
Requires-Dist: PyMySQL
